.gitignore
README
setup.cfg
setup.py
sftpsync/__init__.py
sftpsync.egg-info/PKG-INFO
sftpsync.egg-info/SOURCES.txt
sftpsync.egg-info/dependency_links.txt
sftpsync.egg-info/pbr.json
sftpsync.egg-info/requires.txt
sftpsync.egg-info/top_level.txt
tests/sftpsync_test.py