Metadata-Version: 1.1
Name: sftpsync
Version: 1.0.13
Summary: Sync files and directories over SSH
Home-page: https://github.com/mjirik/sftpsync
Author: Jerome Clerc
Author-email: UNKNOWN
License: UNKNOWN
Keywords: sftp sync
Platform: UNKNOWN
Classifier: Development Status :: 3 - Alpha
Classifier: Intended Audience :: Developers
Classifier: Programming Language :: Python :: 2.7
